bsp/README.md
bsp/__init__.py
bsp/builders/__init__.py
bsp/builders/builder.py
bsp/builders/prompter.py
bsp/bundles/__init__.py
bsp/compatibility.py
bsp/data_generators.py
bsp/data_model/__init__.py
bsp/data_model/base.py
bsp/data_model/bigraph.py
bsp/data_model/quantum.py
bsp/data_model/sed.py
bsp/implementations.py
bsp/io.py
bsp/processes/__init__.py
bsp/processes/amici_process.py
bsp/processes/cobra_process.py
bsp/processes/copasi_process.py
bsp/processes/membrane_process.py
bsp/processes/qaoa_process.py
bsp/processes/qiskit_process.py
bsp/processes/sed_process.py
bsp/processes/simple_membrane_process.py
bsp/processes/smoldyn_process.py
bsp/processes/tellurium_process.py
bsp/quantum/__init__.py
bsp/quantum/test_quantum.ipynb
bsp/registration.py
bsp/schemas/__init__.py
bsp/schemas/config.py
bsp/schemas/types.py
bsp/steps/__init__.py
bsp/steps/main_steps.py
bsp/steps/mongo_emitter.py
bsp/steps/parameter_scan.py
bsp/steps/viz.py
bsp/utils/__init__.py
bsp/utils/base_utils.py
bsp/utils/helpers.py
bsp/utils/membrane_utils.py
bsp/utils/quantum_utils.py
bsp/utils/setup_utils.py
bsp/utils/simularium_utils.py
bsp/viz/__init__.py
bsp/viz/plot.py
tests/MinE.txt
tests/__init__.py
tests/fixtures/README.md
tests/fixtures/bngl/Dolan-PLoS-Comput-Biol-2015-NHEJ/Dolan2015.bngl
tests/fixtures/bngl/Dolan-PLoS-Comput-Biol-2015-NHEJ/Dolan2015.sedml
tests/fixtures/bngl/Dolan-PLoS-Comput-Biol-2015-NHEJ/Figure1.png
tests/fixtures/bngl/Dolan-PLoS-Comput-Biol-2015-NHEJ/expected-results.json
tests/fixtures/bngl/Dolan-PLoS-Comput-Biol-2015-NHEJ/manifest.xml
tests/fixtures/bngl/Dolan-PLoS-Comput-Biol-2015-NHEJ/metadata.rdf
tests/fixtures/bngl/Dolan-PLoS-Comput-Biol-2015-NHEJ/reports.h5
tests/fixtures/bngl/Dolan-PLoS-Comput-Biol-2015-NHEJ.omex
tests/fixtures/bngl/test-bngl/expected-results.json
tests/fixtures/bngl/test-bngl/manifest.xml
tests/fixtures/bngl/test-bngl/metadata.rdf
tests/fixtures/bngl/test-bngl/reports.h5
tests/fixtures/bngl/test-bngl/test.bngl
biosimulator_processes-0.3.19.dist-info/AUTHORS.md
biosimulator_processes-0.3.19.dist-info/LICENSE
biosimulator_processes-0.3.19.dist-info/METADATA
biosimulator_processes-0.3.19.dist-info/WHEEL
biosimulator_processes-0.3.19.dist-info/RECORD
