Metadata-Version: 2.3
Name: biosimulator-processes
Version: 0.3.19
Summary: Core implementations of process-bigraph.composite.Process aligning with BioSimulators simulator tools.
Author: Alex Patrie
Author-email: alexanderpatrie@gmail.com
Requires-Python: >=3.10
Classifier: Programming Language :: Python :: 3
Classifier: Programming Language :: Python :: 3.10
Classifier: Programming Language :: Python :: 3.11
Classifier: Programming Language :: Python :: 3.12
Classifier: Programming Language :: Python :: 3.13
Requires-Dist: h5py
Requires-Dist: ipython
Requires-Dist: pip-autoremove
Requires-Dist: process-bigraph
Requires-Dist: python-dotenv
Requires-Dist: python-libsbml
Requires-Dist: pyyaml
Requires-Dist: requests
Requires-Dist: seaborn
Requires-Dist: toml
